MANIFEST.in
README.markdown
setup.py
htpasswd_cli.egg-info/PKG-INFO
htpasswd_cli.egg-info/SOURCES.txt
htpasswd_cli.egg-info/dependency_links.txt
htpasswd_cli.egg-info/entry_points.txt
htpasswd_cli.egg-info/requires.txt
htpasswd_cli.egg-info/top_level.txt
htpasswdcli/__init__.py
htpasswdcli/cli.py