Metadata-Version: 1.1
Name: htpasswd-cli
Version: 0.1.3
Summary: htpasswd-cli  a CLI, htpasswd(only basic authorization)
Home-page: UNKNOWN
Author: toenobu
Author-email: me@toenobu.name
License: MIT License
Download-URL: https://bitbucket.org/toenobu/htpasswd-cli
Platform: UNKNOWN
Classifier: Development Status :: 3 - Alpha
Classifier: Programming Language :: Python :: 2.7
Classifier: Environment :: Console
Classifier: Intended Audience :: System Administrators
Classifier: License :: OSI Approved :: MIT License
Classifier: Topic :: Terminals
Classifier: Topic :: Utilities
